{
	"sources" : 
	[
		{
			"file" : "/home/masl/Desktop/cvset/opencv-4.4.0/modules/imgcodecs/perf/perf_main.cpp",
			"labels" : 
			[
				"Main",
				"opencv_imgcodecs",
				"PerfTest"
			]
		},
		{
			"file" : "/home/masl/Desktop/cvset/opencv-4.4.0/modules/imgcodecs/perf/perf_precomp.hpp",
			"labels" : 
			[
				"Main",
				"opencv_imgcodecs",
				"PerfTest"
			]
		}
	],
	"target" : 
	{
		"labels" : 
		[
			"Main",
			"opencv_imgcodecs",
			"PerfTest"
		],
		"name" : "opencv_perf_imgcodecs"
	}
}